CDPL/__init__.py
CDPL/_cdpl.so
CDPL/libXau.so.6
CDPL/libXau.so.6.0.0
CDPL/libboost_iostreams.so.1.86.0
CDPL/libboost_python312.so.1.86.0
CDPL/libbz2.so.1
CDPL/libbz2.so.1.0.6
CDPL/libcairo.so.2
CDPL/libcairo.so.2.11512.0
CDPL/libcdpl-base.so.1.2
CDPL/libcdpl-biomol.so.1.2
CDPL/libcdpl-chem.so.1.2
CDPL/libcdpl-confgen.so.1.2
CDPL/libcdpl-descr.so.1.2
CDPL/libcdpl-forcefield.so.1.2
CDPL/libcdpl-grail.so.1.2
CDPL/libcdpl-grid.so.1.2
CDPL/libcdpl-math.so.1.2
CDPL/libcdpl-molprop.so.1.2
CDPL/libcdpl-pharm.so.1.2
CDPL/libcdpl-shape.so.1.2
CDPL/libcdpl-util.so.1.2
CDPL/libcdpl-vis.so.1.2
CDPL/libexpat.so.1
CDPL/libexpat.so.1.6.7
CDPL/libfontconfig.so.1
CDPL/libfontconfig.so.1.12.0
CDPL/libfreetype.so.6
CDPL/libfreetype.so.6.16.1
CDPL/libpixman-1.so.0
CDPL/libpixman-1.so.0.38.4
CDPL/libpng16.so.16
CDPL/libpng16.so.16.34.0
CDPL/libuuid.so.1
CDPL/libuuid.so.1.3.0
CDPL/libxcb-render.so.0
CDPL/libxcb-render.so.0.0.0
CDPL/libxcb-shm.so.0
CDPL/libxcb-shm.so.0.0.0
CDPL/libxcb.so.1
CDPL/libxcb.so.1.1.0
CDPL/libz.so.1
CDPL/libz.so.1.2.11
CDPL/Base/Exceptions.py
CDPL/Base/__init__.py
CDPL/Base/_base.so
CDPL/Biomol/__init__.py
CDPL/Biomol/_biomol.so
CDPL/Chem/__init__.py
CDPL/Chem/_chem.so
CDPL/ConfGen/__init__.py
CDPL/ConfGen/_confgen.so
CDPL/Descr/__init__.py
CDPL/Descr/_descr.so
CDPL/ForceField/Exceptions.py
CDPL/ForceField/__init__.py
CDPL/ForceField/_forcefield.so
CDPL/GRAIL/__init__.py
CDPL/GRAIL/_grail.so
CDPL/Grid/__init__.py
CDPL/Grid/_grid.so
CDPL/Math/__init__.py
CDPL/Math/_math.so
CDPL/MolProp/__init__.py
CDPL/MolProp/_molprop.so
CDPL/Pharm/__init__.py
CDPL/Pharm/_pharm.so
CDPL/Shape/__init__.py
CDPL/Shape/_shape.so
CDPL/Util/Functors.py
CDPL/Util/__init__.py
CDPL/Util/_util.so
CDPL/Vis/CairoBackend.py
CDPL/Vis/QtBackend.py
CDPL/Vis/__init__.py
CDPL/Vis/_vis.so
cdpkit-1.2.3.dist-info/METADATA
cdpkit-1.2.3.dist-info/WHEEL
cdpkit-1.2.3.dist-info/top_level.txt
cdpkit-1.2.3.dist-info/RECORD
cdpkit-1.2.3.dist-info/licenses/COPYING
