Metadata-Version: 2.4
Name: CDPKit
Version: 1.2.3
Summary: CDPKit/CDPL Python Bindings
Home-page: https://cdpkit.org
Author: Thomas Seidel
Author-email: thomas.seidel@univie.ac.at
License: LGPLv2
Requires-Python: >=3.6
License-File: COPYING
Requires-Dist: numpy>=1.17
Dynamic: author
Dynamic: author-email
Dynamic: description
Dynamic: description-content-type
Dynamic: home-page
Dynamic: license
Dynamic: license-file
Dynamic: requires-dist
Dynamic: requires-python
Dynamic: summary
